{
  "contracts": {
    "TeamLock": {
      "address": "0x3ecb32F61F3aE8F3dE5511Bc2b781A0dd90A7aa5",
      "constructorCode": "6080604052610fb6806100136000396000f3fe",
      "bodyBytecodeHash": "5b633cc0340d323aea9fee8fe1332197e9bd97071d2cc13cefe154031d8df28d",
      "localBytecodeHash": "cc3f6fec2cd5906f6191c51921bb5868280a25a1fd5e0c347a7b610a85cd7248",
      "deployedBytecodeHash": "cc3f6fec2cd5906f6191c51921bb5868280a25a1fd5e0c347a7b610a85cd7248",
      "types": {
        "t_bool": {
          "id": "t_bool",
          "kind": "elementary",
          "label": "bool"
        },
        "t_uint256": {
          "id": "t_uint256",
          "kind": "elementary",
          "label": "uint256"
        },
        "t_array:50<t_uint256>": {
          "id": "t_array:50<t_uint256>",
          "valueType": "t_uint256",
          "length": "50",
          "kind": "array",
          "label": "uint256[50]"
        },
        "t_address": {
          "id": "t_address",
          "kind": "elementary",
          "label": "address"
        }
      },
      "storage": [
        {
          "contract": "Initializable",
          "path": "@openzeppelin\\upgrades\\contracts\\Initializable.sol",
          "label": "initialized",
          "astId": 8320,
          "type": "t_bool",
          "src": "757:24:35"
        },
        {
          "contract": "Initializable",
          "path": "@openzeppelin\\upgrades\\contracts\\Initializable.sol",
          "label": "initializing",
          "astId": 8322,
          "type": "t_bool",
          "src": "876:25:35"
        },
        {
          "contract": "Initializable",
          "path": "@openzeppelin\\upgrades\\contracts\\Initializable.sol",
          "label": "______gap",
          "astId": 8384,
          "type": "t_array:50<t_uint256>",
          "src": "1982:29:35"
        },
        {
          "contract": "Ownable",
          "path": "@openzeppelin\\contracts-ethereum-package\\contracts\\ownership\\Ownable.sol",
          "label": "_owner",
          "astId": 7680,
          "type": "t_address",
          "src": "526:22:31"
        },
        {
          "contract": "Ownable",
          "path": "@openzeppelin\\contracts-ethereum-package\\contracts\\ownership\\Ownable.sol",
          "label": "______gap",
          "astId": 7793,
          "type": "t_array:50<t_uint256>",
          "src": "2471:29:31"
        },
        {
          "contract": "LidTimeLock",
          "path": "..\\..\\..\\..\\C\\Users\\great\\repos\\lid-buysell-contracts\\contracts\\LidTimeLock.sol",
          "label": "releaseInterval",
          "astId": 1880,
          "type": "t_uint256",
          "src": "536:27:4"
        },
        {
          "contract": "LidTimeLock",
          "path": "..\\..\\..\\..\\C\\Users\\great\\repos\\lid-buysell-contracts\\contracts\\LidTimeLock.sol",
          "label": "releaseStart",
          "astId": 1882,
          "type": "t_uint256",
          "src": "570:24:4"
        },
        {
          "contract": "LidTimeLock",
          "path": "..\\..\\..\\..\\C\\Users\\great\\repos\\lid-buysell-contracts\\contracts\\LidTimeLock.sol",
          "label": "releaseBP",
          "astId": 1884,
          "type": "t_uint256",
          "src": "601:21:4"
        },
        {
          "contract": "LidTimeLock",
          "path": "..\\..\\..\\..\\C\\Users\\great\\repos\\lid-buysell-contracts\\contracts\\LidTimeLock.sol",
          "label": "startingTokens",
          "astId": 1886,
          "type": "t_uint256",
          "src": "631:26:4"
        },
        {
          "contract": "LidTimeLock",
          "path": "..\\..\\..\\..\\C\\Users\\great\\repos\\lid-buysell-contracts\\contracts\\LidTimeLock.sol",
          "label": "claimedTokens",
          "astId": 1888,
          "type": "t_uint256",
          "src": "664:25:4"
        },
        {
          "contract": "LidTimeLock",
          "path": "..\\..\\..\\..\\C\\Users\\great\\repos\\lid-buysell-contracts\\contracts\\LidTimeLock.sol",
          "label": "token",
          "astId": 1890,
          "type": "t_address",
          "src": "698:20:4"
        },
        {
          "contract": "LidTimeLock",
          "path": "..\\..\\..\\..\\C\\Users\\great\\repos\\lid-buysell-contracts\\contracts\\LidTimeLock.sol",
          "label": "releaseWallet",
          "astId": 1892,
          "type": "t_address",
          "src": "727:21:4"
        },
        {
          "contract": "LidTimeLock",
          "path": "..\\..\\..\\..\\C\\Users\\great\\repos\\lid-buysell-contracts\\contracts\\LidTimeLock.sol",
          "label": "presale",
          "astId": 1894,
          "type": "t_address",
          "src": "761:36:4"
        }
      ],
      "warnings": {
        "hasConstructor": false,
        "hasSelfDestruct": false,
        "hasDelegateCall": false,
        "hasInitialValuesInDeclarations": false,
        "uninitializedBaseContracts": [],
        "storageUncheckedVars": [],
        "storageDiff": []
      }
    },
    "ProjectLock": {
      "address": "0xBB6BbB4705c7D2A4536ccd8347309511792E4540",
      "constructorCode": "6080604052610fb6806100136000396000f3fe",
      "bodyBytecodeHash": "5b633cc0340d323aea9fee8fe1332197e9bd97071d2cc13cefe154031d8df28d",
      "localBytecodeHash": "cc3f6fec2cd5906f6191c51921bb5868280a25a1fd5e0c347a7b610a85cd7248",
      "deployedBytecodeHash": "cc3f6fec2cd5906f6191c51921bb5868280a25a1fd5e0c347a7b610a85cd7248",
      "types": {
        "t_bool": {
          "id": "t_bool",
          "kind": "elementary",
          "label": "bool"
        },
        "t_uint256": {
          "id": "t_uint256",
          "kind": "elementary",
          "label": "uint256"
        },
        "t_array:50<t_uint256>": {
          "id": "t_array:50<t_uint256>",
          "valueType": "t_uint256",
          "length": "50",
          "kind": "array",
          "label": "uint256[50]"
        },
        "t_address": {
          "id": "t_address",
          "kind": "elementary",
          "label": "address"
        }
      },
      "storage": [
        {
          "contract": "Initializable",
          "path": "@openzeppelin\\upgrades\\contracts\\Initializable.sol",
          "label": "initialized",
          "astId": 8320,
          "type": "t_bool",
          "src": "757:24:35"
        },
        {
          "contract": "Initializable",
          "path": "@openzeppelin\\upgrades\\contracts\\Initializable.sol",
          "label": "initializing",
          "astId": 8322,
          "type": "t_bool",
          "src": "876:25:35"
        },
        {
          "contract": "Initializable",
          "path": "@openzeppelin\\upgrades\\contracts\\Initializable.sol",
          "label": "______gap",
          "astId": 8384,
          "type": "t_array:50<t_uint256>",
          "src": "1982:29:35"
        },
        {
          "contract": "Ownable",
          "path": "@openzeppelin\\contracts-ethereum-package\\contracts\\ownership\\Ownable.sol",
          "label": "_owner",
          "astId": 7680,
          "type": "t_address",
          "src": "526:22:31"
        },
        {
          "contract": "Ownable",
          "path": "@openzeppelin\\contracts-ethereum-package\\contracts\\ownership\\Ownable.sol",
          "label": "______gap",
          "astId": 7793,
          "type": "t_array:50<t_uint256>",
          "src": "2471:29:31"
        },
        {
          "contract": "LidTimeLock",
          "path": "..\\..\\..\\..\\C\\Users\\great\\repos\\lid-buysell-contracts\\contracts\\LidTimeLock.sol",
          "label": "releaseInterval",
          "astId": 1880,
          "type": "t_uint256",
          "src": "536:27:4"
        },
        {
          "contract": "LidTimeLock",
          "path": "..\\..\\..\\..\\C\\Users\\great\\repos\\lid-buysell-contracts\\contracts\\LidTimeLock.sol",
          "label": "releaseStart",
          "astId": 1882,
          "type": "t_uint256",
          "src": "570:24:4"
        },
        {
          "contract": "LidTimeLock",
          "path": "..\\..\\..\\..\\C\\Users\\great\\repos\\lid-buysell-contracts\\contracts\\LidTimeLock.sol",
          "label": "releaseBP",
          "astId": 1884,
          "type": "t_uint256",
          "src": "601:21:4"
        },
        {
          "contract": "LidTimeLock",
          "path": "..\\..\\..\\..\\C\\Users\\great\\repos\\lid-buysell-contracts\\contracts\\LidTimeLock.sol",
          "label": "startingTokens",
          "astId": 1886,
          "type": "t_uint256",
          "src": "631:26:4"
        },
        {
          "contract": "LidTimeLock",
          "path": "..\\..\\..\\..\\C\\Users\\great\\repos\\lid-buysell-contracts\\contracts\\LidTimeLock.sol",
          "label": "claimedTokens",
          "astId": 1888,
          "type": "t_uint256",
          "src": "664:25:4"
        },
        {
          "contract": "LidTimeLock",
          "path": "..\\..\\..\\..\\C\\Users\\great\\repos\\lid-buysell-contracts\\contracts\\LidTimeLock.sol",
          "label": "token",
          "astId": 1890,
          "type": "t_address",
          "src": "698:20:4"
        },
        {
          "contract": "LidTimeLock",
          "path": "..\\..\\..\\..\\C\\Users\\great\\repos\\lid-buysell-contracts\\contracts\\LidTimeLock.sol",
          "label": "releaseWallet",
          "astId": 1892,
          "type": "t_address",
          "src": "727:21:4"
        },
        {
          "contract": "LidTimeLock",
          "path": "..\\..\\..\\..\\C\\Users\\great\\repos\\lid-buysell-contracts\\contracts\\LidTimeLock.sol",
          "label": "presale",
          "astId": 1894,
          "type": "t_address",
          "src": "761:36:4"
        }
      ],
      "warnings": {
        "hasConstructor": false,
        "hasSelfDestruct": false,
        "hasDelegateCall": false,
        "hasInitialValuesInDeclarations": false,
        "uninitializedBaseContracts": []
      }
    },
    "LidSimplifiedPresaleTimer": {
      "address": "0x2829F49CB634B848089204a5eFdb5027c1F27474",
      "constructorCode": "6080604052610902806100136000396000f3fe",
      "bodyBytecodeHash": "89494010bfa5df163b27476e4532001048ad59d1e5ecfc86bca681650544d6b7",
      "localBytecodeHash": "034734eb20677f7b9d7fa93b88945dca4c905c748b0241c133a1eda3ca82b920",
      "deployedBytecodeHash": "034734eb20677f7b9d7fa93b88945dca4c905c748b0241c133a1eda3ca82b920",
      "types": {
        "t_bool": {
          "id": "t_bool",
          "kind": "elementary",
          "label": "bool"
        },
        "t_uint256": {
          "id": "t_uint256",
          "kind": "elementary",
          "label": "uint256"
        },
        "t_array:50<t_uint256>": {
          "id": "t_array:50<t_uint256>",
          "valueType": "t_uint256",
          "length": "50",
          "kind": "array",
          "label": "uint256[50]"
        },
        "t_address": {
          "id": "t_address",
          "kind": "elementary",
          "label": "address"
        }
      },
      "storage": [
        {
          "contract": "Initializable",
          "path": "@openzeppelin\\upgrades\\contracts\\Initializable.sol",
          "label": "initialized",
          "astId": 8320,
          "type": "t_bool",
          "src": "757:24:35"
        },
        {
          "contract": "Initializable",
          "path": "@openzeppelin\\upgrades\\contracts\\Initializable.sol",
          "label": "initializing",
          "astId": 8322,
          "type": "t_bool",
          "src": "876:25:35"
        },
        {
          "contract": "Initializable",
          "path": "@openzeppelin\\upgrades\\contracts\\Initializable.sol",
          "label": "______gap",
          "astId": 8384,
          "type": "t_array:50<t_uint256>",
          "src": "1982:29:35"
        },
        {
          "contract": "Ownable",
          "path": "@openzeppelin\\contracts-ethereum-package\\contracts\\ownership\\Ownable.sol",
          "label": "_owner",
          "astId": 7680,
          "type": "t_address",
          "src": "526:22:31"
        },
        {
          "contract": "Ownable",
          "path": "@openzeppelin\\contracts-ethereum-package\\contracts\\ownership\\Ownable.sol",
          "label": "______gap",
          "astId": 7793,
          "type": "t_array:50<t_uint256>",
          "src": "2471:29:31"
        },
        {
          "contract": "LidSimplifiedPresaleTimer",
          "path": "..\\..\\..\\..\\C\\Users\\great\\repos\\lid-buysell-contracts\\contracts\\LidSimplifiedPresaleTimer.sol",
          "label": "startTime",
          "astId": 1728,
          "type": "t_uint256",
          "src": "437:21:3"
        },
        {
          "contract": "LidSimplifiedPresaleTimer",
          "path": "..\\..\\..\\..\\C\\Users\\great\\repos\\lid-buysell-contracts\\contracts\\LidSimplifiedPresaleTimer.sol",
          "label": "endTime",
          "astId": 1730,
          "type": "t_uint256",
          "src": "465:19:3"
        },
        {
          "contract": "LidSimplifiedPresaleTimer",
          "path": "..\\..\\..\\..\\C\\Users\\great\\repos\\lid-buysell-contracts\\contracts\\LidSimplifiedPresaleTimer.sol",
          "label": "hardCapTimer",
          "astId": 1732,
          "type": "t_uint256",
          "src": "491:24:3"
        },
        {
          "contract": "LidSimplifiedPresaleTimer",
          "path": "..\\..\\..\\..\\C\\Users\\great\\repos\\lid-buysell-contracts\\contracts\\LidSimplifiedPresaleTimer.sol",
          "label": "softCap",
          "astId": 1734,
          "type": "t_uint256",
          "src": "522:19:3"
        },
        {
          "contract": "LidSimplifiedPresaleTimer",
          "path": "..\\..\\..\\..\\C\\Users\\great\\repos\\lid-buysell-contracts\\contracts\\LidSimplifiedPresaleTimer.sol",
          "label": "presale",
          "astId": 1736,
          "type": "t_address",
          "src": "548:22:3"
        }
      ],
      "warnings": {
        "hasConstructor": false,
        "hasSelfDestruct": false,
        "hasDelegateCall": false,
        "hasInitialValuesInDeclarations": false,
        "uninitializedBaseContracts": []
      }
    },
    "LidSimplifiedPresaleRedeemer": {
      "address": "0x4Be581f958b02C0ec90bdB25a67964ecf6F7f38a",
      "constructorCode": "6080604052611695806100136000396000f3fe",
      "bodyBytecodeHash": "60572b5a6dd2e135fbf83397c9cd11912d1280c2f3a948887a31e622219e15e3",
      "localBytecodeHash": "9d9883afd6af545d7309fe1ee40868690e550778408010bccf650d22f4f197a6",
      "deployedBytecodeHash": "9d9883afd6af545d7309fe1ee40868690e550778408010bccf650d22f4f197a6",
      "types": {
        "t_bool": {
          "id": "t_bool",
          "kind": "elementary",
          "label": "bool"
        },
        "t_uint256": {
          "id": "t_uint256",
          "kind": "elementary",
          "label": "uint256"
        },
        "t_array:50<t_uint256>": {
          "id": "t_array:50<t_uint256>",
          "valueType": "t_uint256",
          "length": "50",
          "kind": "array",
          "label": "uint256[50]"
        },
        "t_address": {
          "id": "t_address",
          "kind": "elementary",
          "label": "address"
        },
        "t_array:dyn<t_uint256>": {
          "id": "t_array:dyn<t_uint256>",
          "valueType": "t_uint256",
          "length": "dyn",
          "kind": "array",
          "label": "uint256[]"
        },
        "t_mapping<t_uint256>": {
          "id": "t_mapping<t_uint256>",
          "valueType": "t_uint256",
          "label": "mapping(key => uint256)",
          "kind": "mapping"
        }
      },
      "storage": [
        {
          "contract": "Initializable",
          "path": "@openzeppelin\\upgrades\\contracts\\Initializable.sol",
          "label": "initialized",
          "astId": 8320,
          "type": "t_bool",
          "src": "757:24:35"
        },
        {
          "contract": "Initializable",
          "path": "@openzeppelin\\upgrades\\contracts\\Initializable.sol",
          "label": "initializing",
          "astId": 8322,
          "type": "t_bool",
          "src": "876:25:35"
        },
        {
          "contract": "Initializable",
          "path": "@openzeppelin\\upgrades\\contracts\\Initializable.sol",
          "label": "______gap",
          "astId": 8384,
          "type": "t_array:50<t_uint256>",
          "src": "1982:29:35"
        },
        {
          "contract": "Ownable",
          "path": "@openzeppelin\\contracts-ethereum-package\\contracts\\ownership\\Ownable.sol",
          "label": "_owner",
          "astId": 7680,
          "type": "t_address",
          "src": "526:22:31"
        },
        {
          "contract": "Ownable",
          "path": "@openzeppelin\\contracts-ethereum-package\\contracts\\ownership\\Ownable.sol",
          "label": "______gap",
          "astId": 7793,
          "type": "t_array:50<t_uint256>",
          "src": "2471:29:31"
        },
        {
          "contract": "LidSimplifiedPresaleRedeemer",
          "path": "..\\..\\..\\..\\C\\Users\\great\\repos\\lid-buysell-contracts\\contracts\\LidSimplifiedPresaleRedeemer.sol",
          "label": "redeemBP",
          "astId": 1071,
          "type": "t_uint256",
          "src": "712:20:2"
        },
        {
          "contract": "LidSimplifiedPresaleRedeemer",
          "path": "..\\..\\..\\..\\C\\Users\\great\\repos\\lid-buysell-contracts\\contracts\\LidSimplifiedPresaleRedeemer.sol",
          "label": "redeemInterval",
          "astId": 1073,
          "type": "t_uint256",
          "src": "739:26:2"
        },
        {
          "contract": "LidSimplifiedPresaleRedeemer",
          "path": "..\\..\\..\\..\\C\\Users\\great\\repos\\lid-buysell-contracts\\contracts\\LidSimplifiedPresaleRedeemer.sol",
          "label": "bonusRangeStart",
          "astId": 1076,
          "type": "t_array:dyn<t_uint256>",
          "src": "774:29:2"
        },
        {
          "contract": "LidSimplifiedPresaleRedeemer",
          "path": "..\\..\\..\\..\\C\\Users\\great\\repos\\lid-buysell-contracts\\contracts\\LidSimplifiedPresaleRedeemer.sol",
          "label": "bonusRangeBP",
          "astId": 1079,
          "type": "t_array:dyn<t_uint256>",
          "src": "810:26:2"
        },
        {
          "contract": "LidSimplifiedPresaleRedeemer",
          "path": "..\\..\\..\\..\\C\\Users\\great\\repos\\lid-buysell-contracts\\contracts\\LidSimplifiedPresaleRedeemer.sol",
          "label": "currentBonusIndex",
          "astId": 1081,
          "type": "t_uint256",
          "src": "843:29:2"
        },
        {
          "contract": "LidSimplifiedPresaleRedeemer",
          "path": "..\\..\\..\\..\\C\\Users\\great\\repos\\lid-buysell-contracts\\contracts\\LidSimplifiedPresaleRedeemer.sol",
          "label": "totalShares",
          "astId": 1083,
          "type": "t_uint256",
          "src": "881:23:2"
        },
        {
          "contract": "LidSimplifiedPresaleRedeemer",
          "path": "..\\..\\..\\..\\C\\Users\\great\\repos\\lid-buysell-contracts\\contracts\\LidSimplifiedPresaleRedeemer.sol",
          "label": "totalDepositors",
          "astId": 1085,
          "type": "t_uint256",
          "src": "911:27:2"
        },
        {
          "contract": "LidSimplifiedPresaleRedeemer",
          "path": "..\\..\\..\\..\\C\\Users\\great\\repos\\lid-buysell-contracts\\contracts\\LidSimplifiedPresaleRedeemer.sol",
          "label": "accountDeposits",
          "astId": 1089,
          "type": "t_mapping<t_uint256>",
          "src": "945:47:2"
        },
        {
          "contract": "LidSimplifiedPresaleRedeemer",
          "path": "..\\..\\..\\..\\C\\Users\\great\\repos\\lid-buysell-contracts\\contracts\\LidSimplifiedPresaleRedeemer.sol",
          "label": "accountShares",
          "astId": 1093,
          "type": "t_mapping<t_uint256>",
          "src": "999:45:2"
        },
        {
          "contract": "LidSimplifiedPresaleRedeemer",
          "path": "..\\..\\..\\..\\C\\Users\\great\\repos\\lid-buysell-contracts\\contracts\\LidSimplifiedPresaleRedeemer.sol",
          "label": "accountClaimedTokens",
          "astId": 1097,
          "type": "t_mapping<t_uint256>",
          "src": "1051:52:2"
        },
        {
          "contract": "LidSimplifiedPresaleRedeemer",
          "path": "..\\..\\..\\..\\C\\Users\\great\\repos\\lid-buysell-contracts\\contracts\\LidSimplifiedPresaleRedeemer.sol",
          "label": "presale",
          "astId": 1099,
          "type": "t_address",
          "src": "1112:23:2"
        }
      ],
      "warnings": {
        "hasConstructor": false,
        "hasSelfDestruct": false,
        "hasDelegateCall": false,
        "hasInitialValuesInDeclarations": false,
        "uninitializedBaseContracts": []
      }
    },
    "LidSimplifiedPresale": {
      "address": "0xE4eFe7f289fC5035d4d8e404e2e64fCAE42e1E35",
      "constructorCode": "60806040526138ae806100136000396000f3fe",
      "bodyBytecodeHash": "f685c435b13262468890f1cfe399bc87728b726f3799c2185c3063fe5a63b96f",
      "localBytecodeHash": "f8c4ecbbf8e9ffd14d419b0f069e88178051c24b44864e61cbfe570f44afccb1",
      "deployedBytecodeHash": "f8c4ecbbf8e9ffd14d419b0f069e88178051c24b44864e61cbfe570f44afccb1",
      "types": {
        "t_bool": {
          "id": "t_bool",
          "kind": "elementary",
          "label": "bool"
        },
        "t_uint256": {
          "id": "t_uint256",
          "kind": "elementary",
          "label": "uint256"
        },
        "t_array:50<t_uint256>": {
          "id": "t_array:50<t_uint256>",
          "valueType": "t_uint256",
          "length": "50",
          "kind": "array",
          "label": "uint256[50]"
        },
        "t_address": {
          "id": "t_address",
          "kind": "elementary",
          "label": "address"
        },
        "t_struct<Roles.Role>": {
          "id": "t_struct<Roles.Role>",
          "kind": "struct",
          "label": "Roles.Role",
          "members": [
            {
              "label": "bearer",
              "astId": 7180,
              "type": "t_mapping<t_bool>",
              "src": "150:32:27"
            }
          ]
        },
        "t_mapping<t_bool>": {
          "id": "t_mapping<t_bool>",
          "valueType": "t_bool",
          "label": "mapping(key => bool)",
          "kind": "mapping"
        },
        "t_array:dyn<t_address>": {
          "id": "t_array:dyn<t_address>",
          "valueType": "t_address",
          "length": "dyn",
          "kind": "array",
          "label": "address[]"
        },
        "t_array:dyn<t_uint256>": {
          "id": "t_array:dyn<t_uint256>",
          "valueType": "t_uint256",
          "length": "dyn",
          "kind": "array",
          "label": "uint256[]"
        },
        "t_address_payable": {
          "id": "t_address_payable",
          "kind": "elementary",
          "label": "address payable"
        },
        "t_mapping<t_uint256>": {
          "id": "t_mapping<t_uint256>",
          "valueType": "t_uint256",
          "label": "mapping(key => uint256)",
          "kind": "mapping"
        }
      },
      "storage": [
        {
          "contract": "Initializable",
          "path": "@openzeppelin\\upgrades\\contracts\\Initializable.sol",
          "label": "initialized",
          "astId": 8320,
          "type": "t_bool",
          "src": "757:24:35"
        },
        {
          "contract": "Initializable",
          "path": "@openzeppelin\\upgrades\\contracts\\Initializable.sol",
          "label": "initializing",
          "astId": 8322,
          "type": "t_bool",
          "src": "876:25:35"
        },
        {
          "contract": "Initializable",
          "path": "@openzeppelin\\upgrades\\contracts\\Initializable.sol",
          "label": "______gap",
          "astId": 8384,
          "type": "t_array:50<t_uint256>",
          "src": "1982:29:35"
        },
        {
          "contract": "Ownable",
          "path": "@openzeppelin\\contracts-ethereum-package\\contracts\\ownership\\Ownable.sol",
          "label": "_owner",
          "astId": 7680,
          "type": "t_address",
          "src": "526:22:31"
        },
        {
          "contract": "Ownable",
          "path": "@openzeppelin\\contracts-ethereum-package\\contracts\\ownership\\Ownable.sol",
          "label": "______gap",
          "astId": 7793,
          "type": "t_array:50<t_uint256>",
          "src": "2471:29:31"
        },
        {
          "contract": "ReentrancyGuard",
          "path": "@openzeppelin\\contracts-ethereum-package\\contracts\\utils\\ReentrancyGuard.sol",
          "label": "_guardCounter",
          "astId": 8282,
          "type": "t_uint256",
          "src": "733:29:34"
        },
        {
          "contract": "ReentrancyGuard",
          "path": "@openzeppelin\\contracts-ethereum-package\\contracts\\utils\\ReentrancyGuard.sol",
          "label": "______gap",
          "astId": 8315,
          "type": "t_array:50<t_uint256>",
          "src": "1563:29:34"
        },
        {
          "contract": "PauserRole",
          "path": "@openzeppelin\\contracts-ethereum-package\\contracts\\access\\roles\\PauserRole.sol",
          "label": "_pausers",
          "astId": 7277,
          "type": "t_struct<Roles.Role>",
          "src": "327:27:28"
        },
        {
          "contract": "PauserRole",
          "path": "@openzeppelin\\contracts-ethereum-package\\contracts\\access\\roles\\PauserRole.sol",
          "label": "______gap",
          "astId": 7377,
          "type": "t_array:50<t_uint256>",
          "src": "1193:29:28"
        },
        {
          "contract": "Pausable",
          "path": "@openzeppelin\\contracts-ethereum-package\\contracts\\lifecycle\\Pausable.sol",
          "label": "_paused",
          "astId": 7399,
          "type": "t_bool",
          "src": "909:20:29"
        },
        {
          "contract": "Pausable",
          "path": "@openzeppelin\\contracts-ethereum-package\\contracts\\lifecycle\\Pausable.sol",
          "label": "______gap",
          "astId": 7482,
          "type": "t_array:50<t_uint256>",
          "src": "2163:29:29"
        },
        {
          "contract": "LidSimplifiedPresale",
          "path": "..\\..\\..\\..\\C\\Users\\great\\repos\\lid-buysell-contracts\\contracts\\LidSimplifiedPresale.sol",
          "label": "maxBuyPerAddress",
          "astId": 28,
          "type": "t_uint256",
          "src": "906:28:0"
        },
        {
          "contract": "LidSimplifiedPresale",
          "path": "..\\..\\..\\..\\C\\Users\\great\\repos\\lid-buysell-contracts\\contracts\\LidSimplifiedPresale.sol",
          "label": "referralBP",
          "astId": 30,
          "type": "t_uint256",
          "src": "943:22:0"
        },
        {
          "contract": "LidSimplifiedPresale",
          "path": "..\\..\\..\\..\\C\\Users\\great\\repos\\lid-buysell-contracts\\contracts\\LidSimplifiedPresale.sol",
          "label": "uniswapEthBP",
          "astId": 32,
          "type": "t_uint256",
          "src": "974:24:0"
        },
        {
          "contract": "LidSimplifiedPresale",
          "path": "..\\..\\..\\..\\C\\Users\\great\\repos\\lid-buysell-contracts\\contracts\\LidSimplifiedPresale.sol",
          "label": "lidEthBP",
          "astId": 34,
          "type": "t_uint256",
          "src": "1005:20:0"
        },
        {
          "contract": "LidSimplifiedPresale",
          "path": "..\\..\\..\\..\\C\\Users\\great\\repos\\lid-buysell-contracts\\contracts\\LidSimplifiedPresale.sol",
          "label": "uniswapTokenBP",
          "astId": 36,
          "type": "t_uint256",
          "src": "1034:26:0"
        },
        {
          "contract": "LidSimplifiedPresale",
          "path": "..\\..\\..\\..\\C\\Users\\great\\repos\\lid-buysell-contracts\\contracts\\LidSimplifiedPresale.sol",
          "label": "presaleTokenBP",
          "astId": 38,
          "type": "t_uint256",
          "src": "1067:26:0"
        },
        {
          "contract": "LidSimplifiedPresale",
          "path": "..\\..\\..\\..\\C\\Users\\great\\repos\\lid-buysell-contracts\\contracts\\LidSimplifiedPresale.sol",
          "label": "tokenPools",
          "astId": 41,
          "type": "t_array:dyn<t_address>",
          "src": "1100:27:0"
        },
        {
          "contract": "LidSimplifiedPresale",
          "path": "..\\..\\..\\..\\C\\Users\\great\\repos\\lid-buysell-contracts\\contracts\\LidSimplifiedPresale.sol",
          "label": "tokenPoolBPs",
          "astId": 44,
          "type": "t_array:dyn<t_uint256>",
          "src": "1134:26:0"
        },
        {
          "contract": "LidSimplifiedPresale",
          "path": "..\\..\\..\\..\\C\\Users\\great\\repos\\lid-buysell-contracts\\contracts\\LidSimplifiedPresale.sol",
          "label": "hardcap",
          "astId": 46,
          "type": "t_uint256",
          "src": "1169:19:0"
        },
        {
          "contract": "LidSimplifiedPresale",
          "path": "..\\..\\..\\..\\C\\Users\\great\\repos\\lid-buysell-contracts\\contracts\\LidSimplifiedPresale.sol",
          "label": "totalTokens",
          "astId": 48,
          "type": "t_uint256",
          "src": "1195:23:0"
        },
        {
          "contract": "LidSimplifiedPresale",
          "path": "..\\..\\..\\..\\C\\Users\\great\\repos\\lid-buysell-contracts\\contracts\\LidSimplifiedPresale.sol",
          "label": "hasSentToUniswap",
          "astId": 50,
          "type": "t_bool",
          "src": "1227:28:0"
        },
        {
          "contract": "LidSimplifiedPresale",
          "path": "..\\..\\..\\..\\C\\Users\\great\\repos\\lid-buysell-contracts\\contracts\\LidSimplifiedPresale.sol",
          "label": "hasIssuedTokens",
          "astId": 52,
          "type": "t_bool",
          "src": "1262:27:0"
        },
        {
          "contract": "LidSimplifiedPresale",
          "path": "..\\..\\..\\..\\C\\Users\\great\\repos\\lid-buysell-contracts\\contracts\\LidSimplifiedPresale.sol",
          "label": "finalEndTime",
          "astId": 54,
          "type": "t_uint256",
          "src": "1298:24:0"
        },
        {
          "contract": "LidSimplifiedPresale",
          "path": "..\\..\\..\\..\\C\\Users\\great\\repos\\lid-buysell-contracts\\contracts\\LidSimplifiedPresale.sol",
          "label": "finalEth",
          "astId": 56,
          "type": "t_uint256",
          "src": "1329:20:0"
        },
        {
          "contract": "LidSimplifiedPresale",
          "path": "..\\..\\..\\..\\C\\Users\\great\\repos\\lid-buysell-contracts\\contracts\\LidSimplifiedPresale.sol",
          "label": "token",
          "astId": 58,
          "type": "t_address",
          "src": "1358:20:0"
        },
        {
          "contract": "LidSimplifiedPresale",
          "path": "..\\..\\..\\..\\C\\Users\\great\\repos\\lid-buysell-contracts\\contracts\\LidSimplifiedPresale.sol",
          "label": "uniswapRouter",
          "astId": 60,
          "type": "t_address",
          "src": "1385:40:0"
        },
        {
          "contract": "LidSimplifiedPresale",
          "path": "..\\..\\..\\..\\C\\Users\\great\\repos\\lid-buysell-contracts\\contracts\\LidSimplifiedPresale.sol",
          "label": "timer",
          "astId": 62,
          "type": "t_address",
          "src": "1432:39:0"
        },
        {
          "contract": "LidSimplifiedPresale",
          "path": "..\\..\\..\\..\\C\\Users\\great\\repos\\lid-buysell-contracts\\contracts\\LidSimplifiedPresale.sol",
          "label": "redeemer",
          "astId": 64,
          "type": "t_address",
          "src": "1478:45:0"
        },
        {
          "contract": "LidSimplifiedPresale",
          "path": "..\\..\\..\\..\\C\\Users\\great\\repos\\lid-buysell-contracts\\contracts\\LidSimplifiedPresale.sol",
          "label": "access",
          "astId": 66,
          "type": "t_address",
          "src": "1530:41:0"
        },
        {
          "contract": "LidSimplifiedPresale",
          "path": "..\\..\\..\\..\\C\\Users\\great\\repos\\lid-buysell-contracts\\contracts\\LidSimplifiedPresale.sol",
          "label": "lidFund",
          "astId": 68,
          "type": "t_address_payable",
          "src": "1578:31:0"
        },
        {
          "contract": "LidSimplifiedPresale",
          "path": "..\\..\\..\\..\\C\\Users\\great\\repos\\lid-buysell-contracts\\contracts\\LidSimplifiedPresale.sol",
          "label": "earnedReferrals",
          "astId": 72,
          "type": "t_mapping<t_uint256>",
          "src": "1618:47:0"
        },
        {
          "contract": "LidSimplifiedPresale",
          "path": "..\\..\\..\\..\\C\\Users\\great\\repos\\lid-buysell-contracts\\contracts\\LidSimplifiedPresale.sol",
          "label": "referralCounts",
          "astId": 76,
          "type": "t_mapping<t_uint256>",
          "src": "1674:46:0"
        },
        {
          "contract": "LidSimplifiedPresale",
          "path": "..\\..\\..\\..\\C\\Users\\great\\repos\\lid-buysell-contracts\\contracts\\LidSimplifiedPresale.sol",
          "label": "refundedEth",
          "astId": 80,
          "type": "t_mapping<t_uint256>",
          "src": "1729:43:0"
        },
        {
          "contract": "LidSimplifiedPresale",
          "path": "..\\..\\..\\..\\C\\Users\\great\\repos\\lid-buysell-contracts\\contracts\\LidSimplifiedPresale.sol",
          "label": "isRefunding",
          "astId": 82,
          "type": "t_bool",
          "src": "1781:23:0"
        }
      ],
      "warnings": {
        "hasConstructor": false,
        "hasSelfDestruct": false,
        "hasDelegateCall": false,
        "hasInitialValuesInDeclarations": false,
        "uninitializedBaseContracts": []
      }
    }
  },
  "solidityLibs": {},
  "proxies": {
    "lid-simplified-presale-contracts/TeamLock": [
      {
        "address": "0xb0D3eD564709b4ad4aEA55d7f920F59B996b7dc1",
        "version": "1.0.0",
        "implementation": "0x3ecb32F61F3aE8F3dE5511Bc2b781A0dd90A7aa5",
        "admin": "0x0f86A45Fd34ae7Ea4d7c5D564564b7123fdFa961",
        "kind": "Upgradeable"
      }
    ],
    "lid-simplified-presale-contracts/ProjectLock": [
      {
        "address": "0xCD24E046BB791A97056bB227De8A2d66B3Ee6197",
        "version": "1.0.0",
        "implementation": "0xBB6BbB4705c7D2A4536ccd8347309511792E4540",
        "admin": "0x0f86A45Fd34ae7Ea4d7c5D564564b7123fdFa961",
        "kind": "Upgradeable"
      }
    ],
    "lid-simplified-presale-contracts/LidSimplifiedPresaleTimer": [
      {
        "address": "0x3221498f984e25B16582b9dA190cC8DE432e26D7",
        "version": "1.0.0",
        "implementation": "0x2829F49CB634B848089204a5eFdb5027c1F27474",
        "admin": "0x0f86A45Fd34ae7Ea4d7c5D564564b7123fdFa961",
        "kind": "Upgradeable"
      }
    ],
    "lid-simplified-presale-contracts/LidSimplifiedPresaleRedeemer": [
      {
        "address": "0x46527E89389cCDF797E030045275D6F4d8956A79",
        "version": "1.0.0",
        "implementation": "0x4Be581f958b02C0ec90bdB25a67964ecf6F7f38a",
        "admin": "0x0f86A45Fd34ae7Ea4d7c5D564564b7123fdFa961",
        "kind": "Upgradeable"
      }
    ],
    "lid-simplified-presale-contracts/LidSimplifiedPresale": [
      {
        "address": "0xB8e81700FcEbAFF81baB32431bBd19a822156Ed2",
        "version": "1.0.0",
        "implementation": "0xE4eFe7f289fC5035d4d8e404e2e64fCAE42e1E35",
        "admin": "0x0f86A45Fd34ae7Ea4d7c5D564564b7123fdFa961",
        "kind": "Upgradeable"
      }
    ]
  },
  "manifestVersion": "2.2",
  "version": "1.0.0",
  "proxyAdmin": {
    "address": "0x0f86A45Fd34ae7Ea4d7c5D564564b7123fdFa961"
  }
}
